AUTHORS.txt
LICENSE.txt
MANIFEST.in
cascadenik-compile.py
cascadenik-extract-dscfg.py
cascadenik-style.py
requirements.txt
setup.py
cascadenik/__init__.py
cascadenik/compile.py
cascadenik/nonposix.py
cascadenik/output.py
cascadenik/parse.py
cascadenik/safe64.py
cascadenik/sources.py
cascadenik/style.py
cascadenik/tests.py
cascadenik.egg-info/PKG-INFO
cascadenik.egg-info/SOURCES.txt
cascadenik.egg-info/dependency_links.txt
cascadenik.egg-info/not-zip-safe
cascadenik.egg-info/requires.txt
cascadenik.egg-info/top_level.txt