Metadata-Version: 1.1
Name: cascadenik
Version: 2.7.0
Summary: Cascading Stylesheets For Mapnik
Home-page: https://github.com/mapnik/Cascadenik
Author: Michal Migurski
Author-email: mike@teczno.com
License: todo
Keywords: Mapnik,xml,css,mapping
Platform: OS Independent
Classifier: Development Status :: 5 - Production/Stable
Classifier: Environment :: Web Environment
Classifier: Intended Audience :: Developers
Classifier: Intended Audience :: Science/Research
Classifier: Operating System :: OS Independent
Classifier: Programming Language :: Python
Classifier: Topic :: Internet :: WWW/HTTP :: Dynamic Content
Classifier: Topic :: Utilities
Requires: Mapnik
Requires: cssutils
